multitool/__init__.py
multitool/__main__.py
multitool/cls.py
multitool/console.py
multitool/exceptions.py
multitool/silent.py
multitool/utils.py
multitool/verbose.py
multitool/plugins/__init__.py
multitool/plugins/commands.py
tests/__init__.py
tests/test_utils.py
multitool-0.5.0.dist-info/LICENSE
multitool-0.5.0.dist-info/METADATA
multitool-0.5.0.dist-info/WHEEL
multitool-0.5.0.dist-info/entry_points.txt
multitool-0.5.0.dist-info/top_level.txt
multitool-0.5.0.dist-info/RECORD
