Metadata-Version: 2.1
Name: multitool
Version: 0.5.0
Summary: General-purpose command-line interface with plugins support
Home-page: https://github.com/mdelotavo/multitool
Author: Matthew Delotavo
Author-email: matthew.t.delotavo@gmail.com
License: MIT
Platform: UNKNOWN
Classifier: Development Status :: 4 - Beta
Classifier: Environment :: Console
Classifier: Intended Audience :: Developers
Classifier: License :: OSI Approved :: MIT License
Classifier: Operating System :: OS Independent
Classifier: Programming Language :: Python :: 3.7
Requires-Python: >=3.7
License-File: LICENSE
Requires-Dist: click-aliases>=1.0.1
Requires-Dist: click-option-group>=0.5.5
Requires-Dist: click>=8.1.3
Requires-Dist: gitpython>=3.1.30
